AUTHORS.rst
CONTRIBUTING.rst
HISTORY.rst
LICENSE
MANIFEST.in
README.rst
setup.py
django_gaekit.egg-info/PKG-INFO
django_gaekit.egg-info/SOURCES.txt
django_gaekit.egg-info/dependency_links.txt
django_gaekit.egg-info/not-zip-safe
django_gaekit.egg-info/requires.txt
django_gaekit.egg-info/top_level.txt
gaekit/__init__.py
gaekit/boot.py
gaekit/caches.py
gaekit/drf_extensions_extensions.py
gaekit/models.py
gaekit/storages.py