Metadata-Version: 1.1
Name: django-gaekit
Version: 0.2.7
Summary: Collection of backends, wrappers and utilities to enquicken django development on Google App Engine
Home-page: https://github.com/Beyond-Digital/django-gaekit
Author: George Whewell
Author-email: george@bynd.com
License: BSD
Keywords: django-gaekit
Platform: UNKNOWN
Classifier: Development Status :: 2 - Pre-Alpha
Classifier: Framework :: Django
Classifier: Intended Audience :: Developers
Classifier: License :: OSI Approved :: BSD License
Classifier: Natural Language :: English
Classifier: Programming Language :: Python :: 2
Classifier: Programming Language :: Python :: 2.6
Classifier: Programming Language :: Python :: 2.7
Classifier: Programming Language :: Python :: 3
Classifier: Programming Language :: Python :: 3.3
